pmtoolkit/__init__.py
pmtoolkit/creating_project/CreateProject.py
pmtoolkit/data_assert/DataAssert.py
pmtoolkit/exception/GlobalException.py
pmtoolkit/file_copy/FileCopier.py
pmtoolkit/log/Log.py
pmtoolkit/polling/Polling.py
pmtoolkit/reading_config/ReadingConfig.py
pmtoolkit-1.1.1.dist-info/LICENSE
pmtoolkit-1.1.1.dist-info/METADATA
pmtoolkit-1.1.1.dist-info/WHEEL
pmtoolkit-1.1.1.dist-info/RECORD
